pyfsr/__init__.py
pyfsr/client.py
pyfsr/constants.py
pyfsr/exceptions.py
pyfsr/api/__init__.py
pyfsr/api/alerts.py
pyfsr/api/base.py
pyfsr/api/export_config.py
pyfsr/api/solution_packs.py
pyfsr/auth/__init__.py
pyfsr/auth/api_key.py
pyfsr/auth/base.py
pyfsr/auth/user_pass.py
pyfsr/utils/__init__.py
pyfsr/utils/file_operations.py
pyfsr-0.2.2.dist-info/METADATA
pyfsr-0.2.2.dist-info/WHEEL
pyfsr-0.2.2.dist-info/licenses/LICENSE
pyfsr-0.2.2.dist-info/RECORD
